paddlets/__init__.py
paddlets/analysis/__init__.py
paddlets/analysis/analysis_report.py
paddlets/analysis/base.py
paddlets/analysis/base_analyzers.py
paddlets/analysis/frequency_domain.py
paddlets/analysis/time_domain.py
paddlets/automl/__init__.py
paddlets/automl/autots.py
paddlets/automl/optimize_runner.py
paddlets/automl/search_space_configer.py
paddlets/automl/searcher.py
paddlets/datasets/__init__.py
paddlets/datasets/splitter.py
paddlets/datasets/tsdataset.py
paddlets/datasets/repository/__init__.py
paddlets/datasets/repository/_data_config.py
paddlets/datasets/repository/base.py
paddlets/ensemble/__init__.py
paddlets/ensemble/base.py
paddlets/ensemble/ensemble_forecaster_base.py
paddlets/ensemble/stacking_ensemble.py
paddlets/ensemble/stacking_ensemble_forecaster.py
paddlets/ensemble/weighting_ensemble.py
paddlets/ensemble/weighting_ensemble_forecaster.py
paddlets/logger/__init__.py
paddlets/logger/logger.py
paddlets/metrics/__init__.py
paddlets/metrics/base.py
paddlets/metrics/metrics.py
paddlets/metrics/utils.py
paddlets/models/__init__.py
paddlets/models/base.py
paddlets/models/data_adapter.py
paddlets/models/ml_model_wrapper.py
paddlets/models/model_loader.py
paddlets/models/utils.py
paddlets/models/anomaly/__init__.py
paddlets/models/anomaly/dl/__init__.py
paddlets/models/anomaly/dl/anomaly_base.py
paddlets/models/anomaly/dl/anomaly_transformer.py
paddlets/models/anomaly/dl/autoencoder.py
paddlets/models/anomaly/dl/mtad_gat.py
paddlets/models/anomaly/dl/usad.py
paddlets/models/anomaly/dl/utils.py
paddlets/models/anomaly/dl/vae.py
paddlets/models/anomaly/dl/_anomaly_transformer/__init__.py
paddlets/models/anomaly/dl/_anomaly_transformer/attention.py
paddlets/models/anomaly/dl/_anomaly_transformer/embedding.py
paddlets/models/anomaly/dl/_anomaly_transformer/encoder.py
paddlets/models/anomaly/dl/_ed/__init__.py
paddlets/models/anomaly/dl/_ed/ed.py
paddlets/models/anomaly/dl/_mtad_gat/__init__.py
paddlets/models/anomaly/dl/_mtad_gat/attention.py
paddlets-1.1.0.dist-info/LICENSE
paddlets-1.1.0.dist-info/METADATA
paddlets-1.1.0.dist-info/WHEEL
paddlets-1.1.0.dist-info/top_level.txt
paddlets-1.1.0.dist-info/RECORD
