Metadata-Version: 2.1
Name: paddlets
Version: 1.1.0
Summary: PaddleTS (Paddle Time Series Tool),            PaddlePaddle-based Time Series Modeling in Python
Home-page: https://github.com/PaddlePaddle/PaddleTS
Maintainer: paddlets Team
Maintainer-email: paddlets@baidu.com
License: LICENSE
Platform: UNKNOWN
Classifier: Programming Language :: Python :: 3
Classifier: Programming Language :: Python :: 3.7
Classifier: Programming Language :: Python :: 3.8
Classifier: Programming Language :: Python :: 3.9
Classifier: License :: OSI Approved :: Apache Software License
Classifier: Operating System :: OS Independent
Requires-Python: >=3.7
Requires-Dist: numpy (<=1.19.5,>=1.17.0)
Requires-Dist: pandas (<=1.3.5,>=0.25.0)
Requires-Dist: scikit-learn (>=0.24.1)
Requires-Dist: chinese-calendar (==1.8.0)
Requires-Dist: python-docx
Requires-Dist: matplotlib (>=3.1.2)
Requires-Dist: PyWavelets (<=1.3.0,>=1.1.0)
Requires-Dist: statsmodels (<=0.12.2,>=0.10.2)
Requires-Dist: scipy (<=1.7.3,>=1.5.0)
Requires-Dist: tqdm
Requires-Dist: pyod (>=1.0.5)
Requires-Dist: seaborn (>=0.11.2)
Requires-Dist: shap (>=0.40.0)
Requires-Dist: jinja2
Requires-Dist: IPython
Requires-Dist: more-itertools
Provides-Extra: all
Requires-Dist: numpy (<=1.19.5,>=1.17.0) ; extra == 'all'
Requires-Dist: pandas (<=1.3.5,>=0.25.0) ; extra == 'all'
Requires-Dist: scikit-learn (>=0.24.1) ; extra == 'all'
Requires-Dist: chinese-calendar (==1.8.0) ; extra == 'all'
Requires-Dist: python-docx ; extra == 'all'
Requires-Dist: matplotlib (>=3.1.2) ; extra == 'all'
Requires-Dist: PyWavelets (<=1.3.0,>=1.1.0) ; extra == 'all'
Requires-Dist: statsmodels (<=0.12.2,>=0.10.2) ; extra == 'all'
Requires-Dist: scipy (<=1.7.3,>=1.5.0) ; extra == 'all'
Requires-Dist: tqdm ; extra == 'all'
Requires-Dist: pyod (>=1.0.5) ; extra == 'all'
Requires-Dist: seaborn (>=0.11.2) ; extra == 'all'
Requires-Dist: shap (>=0.40.0) ; extra == 'all'
Requires-Dist: jinja2 ; extra == 'all'
Requires-Dist: IPython ; extra == 'all'
Requires-Dist: more-itertools ; extra == 'all'
Requires-Dist: protobuf (<=3.20.0,>=3.1.0) ; extra == 'all'
Requires-Dist: paddlepaddle (<2.4.0,>=2.3.0) ; extra == 'all'
Requires-Dist: ray[tune] (>=1.13.0) ; extra == 'all'
Requires-Dist: optuna (>=2.10.1) ; extra == 'all'
Requires-Dist: FLAML (>=0.10.0) ; extra == 'all'
Requires-Dist: hpbandster (>=0.7.4) ; extra == 'all'
Requires-Dist: ConfigSpace (>=0.5.0) ; extra == 'all'
Provides-Extra: autots
Requires-Dist: ray[tune] (>=1.13.0) ; extra == 'autots'
Requires-Dist: optuna (>=2.10.1) ; extra == 'autots'
Requires-Dist: FLAML (>=0.10.0) ; extra == 'autots'
Requires-Dist: hpbandster (>=0.7.4) ; extra == 'autots'
Requires-Dist: ConfigSpace (>=0.5.0) ; extra == 'autots'
Provides-Extra: paddle
Requires-Dist: protobuf (<=3.20.0,>=3.1.0) ; extra == 'paddle'
Requires-Dist: paddlepaddle (<2.4.0,>=2.3.0) ; extra == 'paddle'
